evolved5g/__init__.py
evolved5g/cli.py
evolved5g/cli_helper.py
evolved5g/nef_and_tsn_api_service_validation_pipeline.py
evolved5g/sdk.py
evolved5g/utils.py
evolved5g/swagger_client/__init__.py
evolved5g/swagger_client/api_client.py
evolved5g/swagger_client/configuration.py
evolved5g/swagger_client/rest.py
evolved5g/swagger_client/api/__init__.py
evolved5g/swagger_client/api/cells_api.py
evolved5g/swagger_client/api/default_api.py
evolved5g/swagger_client/api/g_n_bs_api.py
evolved5g/swagger_client/api/location_frontend_api.py
evolved5g/swagger_client/api/login_api.py
evolved5g/swagger_client/api/monitoring_event_api_api.py
evolved5g/swagger_client/api/paths_api.py
evolved5g/swagger_client/api/qo_s_information_api.py
evolved5g/swagger_client/api/session_with_qo_s_api_api.py
evolved5g/swagger_client/api/u_es_api.py
evolved5g/swagger_client/api/ui_api.py
evolved5g/swagger_client/api/users_api.py
evolved5g/swagger_client/api/utils_api.py
evolved5g/swagger_client/models/__init__.py
evolved5g/swagger_client/models/accumulated_usage.py
evolved5g/swagger_client/models/all_of_u_es_speed.py
evolved5g/swagger_client/models/all_of_ue_create_speed.py
evolved5g/swagger_client/models/all_of_ue_speed.py
evolved5g/swagger_client/models/all_of_ue_update_speed.py
evolved5g/swagger_client/models/all_of_user_plane_event_report_event.py
evolved5g/swagger_client/models/as_session_with_qo_s_subscription.py
evolved5g/swagger_client/models/as_session_with_qo_s_subscription_create.py
evolved5g/swagger_client/models/body_create_user_open_api_v1_users_open_post.py
evolved5g/swagger_client/models/body_login_access_token_api_v1_login_access_token_post.py
evolved5g/swagger_client/models/body_reset_password_api_v1_reset_password_post.py
evolved5g/swagger_client/models/body_update_user_me_api_v1_users_me_put.py
evolved5g/swagger_client/models/cell.py
evolved5g/swagger_client/models/cell_create.py
evolved5g/swagger_client/models/cell_update.py
evolved5g/swagger_client/models/gnb.py
evolved5g-1.0.13.dist-info/LICENSE
evolved5g-1.0.13.dist-info/METADATA
evolved5g-1.0.13.dist-info/WHEEL
evolved5g-1.0.13.dist-info/entry_points.txt
evolved5g-1.0.13.dist-info/top_level.txt
evolved5g-1.0.13.dist-info/RECORD
