Metadata-Version: 2.1
Name: evolved5g
Version: 1.0.13
Summary: Evolved5G CLI prototype 
Home-page: https://github.com/EVOLVED-5G/SDK-CLI
Author: EVOLVED5G project
License: Apache Software License 2.0
Keywords: evolved5g
Platform: UNKNOWN
Classifier: Development Status :: 3 - Alpha
Classifier: Intended Audience :: Developers
Classifier: License :: OSI Approved :: Apache Software License
Classifier: Natural Language :: English
Classifier: Programming Language :: Python :: 3
Classifier: Programming Language :: Python :: 3.6
Classifier: Programming Language :: Python :: 3.7
Classifier: Programming Language :: Python :: 3.8
Requires-Python: >=3.7
